Metadata-Version: 2.4
Name: anisoap
Version: 0.1.1
Summary: A package for computing anisotropic extensions to the SOAP formalism
Author: Kevin Kazuki Huguenin-Dumittan, Jigyasa Nigam, Yong-Cheol Cho, Lucas Ortengren, Seonwoo Hwang, Rose K. Cersonsky
Author-email: Arthur Lin <alin62@wisc.edu>
License:                                  Apache License
Classifier: Development Status :: 3 - Alpha
Classifier: Intended Audience :: Science/Research
Classifier: Topic :: Scientific/Engineering
Classifier: Natural Language :: English
Classifier: Programming Language :: Python :: 3
Classifier: Programming Language :: Python :: 3.9
Classifier: Programming Language :: Python :: 3.10
Classifier: Programming Language :: Python :: 3.11
Classifier: Programming Language :: Python :: 3.12
Requires-Python: >=3.9
License-File: LICENSE
Requires-Dist: featomic
Requires-Dist: ase
Requires-Dist: coverage[toml]
Requires-Dist: pytest
Requires-Dist: scipy
Requires-Dist: setuptools-rust
Requires-Dist: tqdm
Requires-Dist: metatensor
Requires-Dist: wigners
Requires-Dist: matplotlib
Requires-Dist: skmatter
Dynamic: license-file
